mailinator/__init__.py
mailinator/client.py
mailinator/constants.py
mailinator/domain/__init__.py
mailinator/domain/domain.py
mailinator/domain/interface.py
mailinator/message/__init__.py
mailinator/message/attachment.py
mailinator/message/inbox.py
mailinator/message/message.py
mailinator/message/part.py
mailinator/message/interface/__init__.py
mailinator/message/interface/get.py
mailinator/rule/__init__.py
mailinator/rule/action.py
mailinator/rule/condition.py
mailinator/rule/interface.py
mailinator/rule/rule.py
tests/__init__.py
mailinator_python_client-0.0.2.dist-info/LICENSE
mailinator_python_client-0.0.2.dist-info/METADATA
mailinator_python_client-0.0.2.dist-info/WHEEL
mailinator_python_client-0.0.2.dist-info/top_level.txt
mailinator_python_client-0.0.2.dist-info/RECORD
