Metadata-Version: 2.1
Name: mailinator-python-client
Version: 0.0.2
Summary: Python Client for the Mailinator Email System https://www.mailinator.com
Home-page: UNKNOWN
Author: Adela Kacso-Vidrean (KVA)
Author-email: adella.neacsu@gmail.com
License: GNU GENERAL PUBLIC LICENSE
Platform: UNKNOWN
Classifier: Environment :: Console
Classifier: Intended Audience :: Developers
Classifier: Operating System :: OS Independent
Classifier: Programming Language :: Python :: 3
Classifier: Programming Language :: Python :: 3.6
Classifier: Programming Language :: Python :: 3.7
Classifier: Programming Language :: Python :: 3.8
Classifier: Topic :: Communications :: Email
Classifier: Topic :: Software Development :: Testing
Classifier: Topic :: Utilities
Requires-Dist: dataclasses (==0.7)
Requires-Dist: requests (>=2.22.0)
Requires-Dist: dataclasses-json
